Metadata-Version: 1.0
Name: norm-binom-distribution
Version: 0.11
Summary: Gaussian & Binomial distributions
Home-page: UNKNOWN
Author: UNKNOWN
Author-email: UNKNOWN
License: UNKNOWN
Platform: UNKNOWN
